gemtide/GemTideApplication.py
gemtide/__init__.py
gemtide/__main__.py
gemtide/templates/footer
gemtide/templates/index
gemtide/templates/macros
gemtide/templates/search
gemtide/templates/station.gmi
gemtide/templates/station.txt
gemtide-0.1.1.dist-info/LICENSE
gemtide-0.1.1.dist-info/METADATA
gemtide-0.1.1.dist-info/WHEEL
gemtide-0.1.1.dist-info/entry_points.txt
gemtide-0.1.1.dist-info/top_level.txt
gemtide-0.1.1.dist-info/RECORD
