Metadata-Version: 2.1
Name: gemtide
Version: 0.1.1
Summary: A Jetforce application for serving information about UK tidal events over the Gemini Protocol
Home-page: https://git.sr.ht/~supergrizzlybear/gemtide
Author: supergrizzlybear
Author-email: supergrizzlybear@protonmail.com
License: Other/Proprietary License
Keywords: gemini
Platform: UNKNOWN
Classifier: Development Status :: 2 - Pre-Alpha
Classifier: Intended Audience :: Developers
Classifier: Operating System :: OS Independent
Classifier: Programming Language :: Python :: 3
Classifier: Topic :: Software Development :: Libraries :: Python Modules
Requires-Python: >=3.7
License-File: LICENSE
Requires-Dist: jetforce
Requires-Dist: aiohttp
Requires-Dist: ukhotides
Requires-Dist: jinja2
Requires-Dist: unicode-slugify
Requires-Dist: pyyaml
